citation/Library.py
citation/Package.py
citation/__init__.py
citation-0.0.2.dist-info/METADATA
citation-0.0.2.dist-info/WHEEL
citation-0.0.2.dist-info/top_level.txt
citation-0.0.2.dist-info/zip-safe
citation-0.0.2.dist-info/RECORD
